kodekloud_downloader/__init__.py
kodekloud_downloader/cli.py
kodekloud_downloader/enums.py
kodekloud_downloader/helpers.py
kodekloud_downloader/main.py
kodekloud_downloader/models/__init__.py
kodekloud_downloader/models/course.py
kodekloud_downloader/models/courses.py
kodekloud_downloader/models/helper.py
kodekloud_downloader/models/quiz.py
kodekloud_downloader-0.1.4.dist-info/METADATA
kodekloud_downloader-0.1.4.dist-info/WHEEL
kodekloud_downloader-0.1.4.dist-info/entry_points.txt
kodekloud_downloader-0.1.4.dist-info/RECORD
