Metadata-Version: 2.1
Name: kodekloud-downloader
Version: 0.1.4
Summary: Simple downloaded for https://kodekloud.com/
Home-page: https://github.com/debakarr/kodekloud-downloader
Author: Roy, Debakar
Author-email: debakar.roy@outlook.com
Requires-Python: >=3.8,<4.0
Classifier: Programming Language :: Python :: 3
Classifier: Programming Language :: Python :: 3.8
Classifier: Programming Language :: Python :: 3.9
Classifier: Programming Language :: Python :: 3.10
Classifier: Programming Language :: Python :: 3.11
Requires-Dist: beautifulsoup4 (>=4.12.2,<5.0.0)
Requires-Dist: click (>=8.1.3,<9.0.0)
Requires-Dist: markdownify (>=0.11.6,<0.12.0)
Requires-Dist: prettytable (>=3.7.0,<4.0.0)
Requires-Dist: pydantic (>=2.9.1,<3.0.0)
Requires-Dist: requests (>=2.28.2,<3.0.0)
Requires-Dist: validators (>=0.20.0,<0.21.0)
Requires-Dist: yt-dlp (>=2023.3.4,<2024.0.0)
Project-URL: Repository, https://github.com/debakarr/kodekloud-downloader
